LICENSE.txt
README.md
setup.cfg
setup.py
kuberender/__init__.py
kuberender/file.py
kuberender/render.py
kuberender/utils.py
kuberender.egg-info/PKG-INFO
kuberender.egg-info/SOURCES.txt
kuberender.egg-info/dependency_links.txt
kuberender.egg-info/entry_points.txt
kuberender.egg-info/requires.txt
kuberender.egg-info/top_level.txt